thot/__init__.py
thot/runner.py
thot/thot.py
thot/utilities.py
thot/db/__init__.py
thot/db/local.py
thot_cli/__init__.py
thot_cli/__main__.py
thot_cli/cmdline.py
thot_cli/runner.py
thot_cli/utilities.py
thot_cli/commands/__init__.py
thot_cli/commands/command.py
thot_cli/commands/run/__init__.py
thot_cli/commands/run/cmd.py
thot_cli/commands/run/runner.py
thot_cli/commands/utils/__init__.py
thot_cli/commands/utils/cmd.py
thot_cli/commands/utils/utilities.py
thot_cli-0.5.1.dist-info/LICENSE
thot_cli-0.5.1.dist-info/METADATA
thot_cli-0.5.1.dist-info/WHEEL
thot_cli-0.5.1.dist-info/entry_points.txt
thot_cli-0.5.1.dist-info/top_level.txt
thot_cli-0.5.1.dist-info/RECORD
