Metadata-Version: 2.1
Name: thot-cli
Version: 0.5.1
Summary: Command line interface for Thot data analysis and management.
Home-page: http://www.thot-data.com
Author: Brian Carlsen
Author-email: carlsen.bri@gmail.com
License: UNKNOWN
Project-URL: Documentation, https://thot-data-docs.readthedocs.io/
Project-URL: Source Code, https://github.com/bicarlsen/thot-data
Project-URL: Bug Tracker, https://github.com/bicarlsen/thot-data/issues
Platform: UNKNOWN
Classifier: Programming Language :: Python :: 3
Classifier: License :: OSI Approved :: GNU General Public License v3 (GPLv3)
Classifier: Operating System :: OS Independent
Requires-Dist: thot-core (>=0.4.9)
Requires-Dist: thot-data (>=0.5.0)
